odoo10_addon_report_qweb_signer-10.0.1.0.1-py2.7-nspkg.pth
odoo/addons/report_qweb_signer/README.rst
odoo/addons/report_qweb_signer/__init__.py
odoo/addons/report_qweb_signer/__manifest__.py
odoo/addons/report_qweb_signer/demo/report_certificate_demo.xml
odoo/addons/report_qweb_signer/demo/report_partner_demo.xml
odoo/addons/report_qweb_signer/i18n/am.po
odoo/addons/report_qweb_signer/i18n/ar.po
odoo/addons/report_qweb_signer/i18n/bg.po
odoo/addons/report_qweb_signer/i18n/bs.po
odoo/addons/report_qweb_signer/i18n/ca.po
odoo/addons/report_qweb_signer/i18n/ca_ES.po
odoo/addons/report_qweb_signer/i18n/cs.po
odoo/addons/report_qweb_signer/i18n/da.po
odoo/addons/report_qweb_signer/i18n/de.po
odoo/addons/report_qweb_signer/i18n/el_GR.po
odoo/addons/report_qweb_signer/i18n/en_GB.po
odoo/addons/report_qweb_signer/i18n/es.po
odoo/addons/report_qweb_signer/i18n/es_AR.po
odoo/addons/report_qweb_signer/i18n/es_CL.po
odoo/addons/report_qweb_signer/i18n/es_CO.po
odoo/addons/report_qweb_signer/i18n/es_CR.po
odoo/addons/report_qweb_signer/i18n/es_DO.po
odoo/addons/report_qweb_signer/i18n/es_EC.po
odoo/addons/report_qweb_signer/i18n/es_ES.po
odoo/addons/report_qweb_signer/i18n/es_MX.po
odoo/addons/report_qweb_signer/i18n/es_PE.po
odoo/addons/report_qweb_signer/i18n/es_PY.po
odoo/addons/report_qweb_signer/i18n/es_VE.po
odoo/addons/report_qweb_signer/i18n/et.po
odoo/addons/report_qweb_signer/i18n/eu.po
odoo/addons/report_qweb_signer/i18n/fa.po
odoo/addons/report_qweb_signer/i18n/fi.po
odoo/addons/report_qweb_signer/i18n/fr.po
odoo/addons/report_qweb_signer/i18n/fr_CA.po
odoo/addons/report_qweb_signer/i18n/fr_CH.po
odoo/addons/report_qweb_signer/i18n/fr_FR.po
odoo/addons/report_qweb_signer/i18n/gl.po
odoo/addons/report_qweb_signer/i18n/gl_ES.po
odoo/addons/report_qweb_signer/i18n/he.po
odoo/addons/report_qweb_signer/i18n/hr.po
odoo/addons/report_qweb_signer/i18n/hr_HR.po
odoo/addons/report_qweb_signer/i18n/hu.po
odoo10_addon_report_qweb_signer-10.0.1.0.1.dist-info/DESCRIPTION.rst
odoo10_addon_report_qweb_signer-10.0.1.0.1.dist-info/METADATA
odoo10_addon_report_qweb_signer-10.0.1.0.1.dist-info/RECORD
odoo10_addon_report_qweb_signer-10.0.1.0.1.dist-info/WHEEL
odoo10_addon_report_qweb_signer-10.0.1.0.1.dist-info/metadata.json
odoo10_addon_report_qweb_signer-10.0.1.0.1.dist-info/namespace_packages.txt
odoo10_addon_report_qweb_signer-10.0.1.0.1.dist-info/top_level.txt
